[
    {
        "dist": 0.0, 
        "alts": {
            "DTM25": 677.7
        }, 
        "easting": 567927.974, 
        "northing": 131069.761
    }, 
    {
        "dist": 337.3, 
        "alts": {
            "DTM25": 712.5
        }, 
        "easting": 568132.52, 
        "northing": 131337.943
    }, 
    {
        "dist": 674.6, 
        "alts": {
            "DTM25": 772.4
        }, 
        "easting": 568337.065, 
        "northing": 131606.124
    }, 
    {
        "dist": 1011.9, 
        "alts": {
            "DTM25": 835.3
        }, 
        "easting": 568541.61, 
        "northing": 131874.306
    }, 
    {
        "dist": 1349.1, 
        "alts": {
            "DTM25": 882.7
        }, 
        "easting": 568746.156, 
        "northing": 132142.488
    }, 
    {
        "dist": 1686.4, 
        "alts": {
            "DTM25": 916.6
        }, 
        "easting": 568950.701, 
        "northing": 132410.67
    }, 
    {
        "dist": 2023.7, 
        "alts": {
            "DTM25": 932.7
        }, 
        "easting": 569155.247, 
        "northing": 132678.852
    }, 
    {
        "dist": 2361.0, 
        "alts": {
            "DTM25": 921.1
        }, 
        "easting": 569359.792, 
        "northing": 132947.033
    }, 
    {
        "dist": 2698.3, 
        "alts": {
            "DTM25": 915.7
        }, 
        "easting": 569564.338, 
        "northing": 133215.215
    }, 
    {
        "dist": 3035.6, 
        "alts": {
            "DTM25": 925.1
        }, 
        "easting": 569768.883, 
        "northing": 133483.397
    }, 
    {
        "dist": 3372.8, 
        "alts": {
            "DTM25": 930.9
        }, 
        "easting": 569973.429, 
        "northing": 133751.579
    }, 
    {
        "dist": 3710.1, 
        "alts": {
            "DTM25": 938.5
        }, 
        "easting": 570177.974, 
        "northing": 134019.761
    }, 
    {
        "dist": 4049.4, 
        "alts": {
            "DTM25": 956.8
        }, 
        "easting": 570517.26, 
        "northing": 134023.332
    }, 
    {
        "dist": 4388.7, 
        "alts": {
            "DTM25": 967.0
        }, 
        "easting": 570856.545, 
        "northing": 134026.904
    }, 
    {
        "dist": 4728.0, 
        "alts": {
            "DTM25": 982.7
        }, 
        "easting": 571195.831, 
        "northing": 134030.475
    }, 
    {
        "dist": 5067.3, 
        "alts": {
            "DTM25": 1037.7
        }, 
        "easting": 571535.117, 
        "northing": 134034.046
    }, 
    {
        "dist": 5406.6, 
        "alts": {
            "DTM25": 1033.8
        }, 
        "easting": 571874.403, 
        "northing": 134037.618
    }, 
    {
        "dist": 5745.9, 
        "alts": {
            "DTM25": 1028.5
        }, 
        "easting": 572213.688, 
        "northing": 134041.189
    }, 
    {
        "dist": 6085.3, 
        "alts": {
            "DTM25": 1034.5
        }, 
        "easting": 572552.974, 
        "northing": 134044.761
    }, 
    {
        "dist": 6424.6, 
        "alts": {
            "DTM25": 1027.3
        }, 
        "easting": 572892.26, 
        "northing": 134048.332
    }, 
    {
        "dist": 6763.9, 
        "alts": {
            "DTM25": 1037.2
        }, 
        "easting": 573231.545, 
        "northing": 134051.904
    }, 
    {
        "dist": 7103.2, 
        "alts": {
            "DTM25": 1065.9
        }, 
        "easting": 573570.831, 
        "northing": 134055.475
    }, 
    {
        "dist": 7442.5, 
        "alts": {
            "DTM25": 1091.7
        }, 
        "easting": 573910.117, 
        "northing": 134059.046
    }, 
    {
        "dist": 7781.8, 
        "alts": {
            "DTM25": 1110.3
        }, 
        "easting": 574249.403, 
        "northing": 134062.618
    }, 
    {
        "dist": 8121.1, 
        "alts": {
            "DTM25": 1130.7
        }, 
        "easting": 574588.688, 
        "northing": 134066.189
    }, 
    {
        "dist": 8460.4, 
        "alts": {
            "DTM25": 1148.7
        }, 
        "easting": 574927.974, 
        "northing": 134069.761
    }, 
    {
        "dist": 8790.7, 
        "alts": {
            "DTM25": 1147.5
        }, 
        "easting": 575254.445, 
        "northing": 134019.761
    }, 
    {
        "dist": 9120.9, 
        "alts": {
            "DTM25": 1147.6
        }, 
        "easting": 575580.915, 
        "northing": 133969.761
    }, 
    {
        "dist": 9451.2, 
        "alts": {
            "DTM25": 1145.1
        }, 
        "easting": 575907.386, 
        "northing": 133919.761
    }, 
    {
        "dist": 9781.5, 
        "alts": {
            "DTM25": 1140.4
        }, 
        "easting": 576233.856, 
        "northing": 133869.761
    }, 
    {
        "dist": 10111.8, 
        "alts": {
            "DTM25": 1145.1
        }, 
        "easting": 576560.327, 
        "northing": 133819.761
    }, 
    {
        "dist": 10442.0, 
        "alts": {
            "DTM25": 1146.5
        }, 
        "easting": 576886.798, 
        "northing": 133769.761
    }, 
    {
        "dist": 10772.3, 
        "alts": {
            "DTM25": 1152.2
        }, 
        "easting": 577213.268, 
        "northing": 133719.761
    }, 
    {
        "dist": 11102.6, 
        "alts": {
            "DTM25": 1160.4
        }, 
        "easting": 577539.739, 
        "northing": 133669.761
    }, 
    {
        "dist": 11432.9, 
        "alts": {
            "DTM25": 1176.0
        }, 
        "easting": 577866.209, 
        "northing": 133619.761
    }, 
    {
        "dist": 11763.2, 
        "alts": {
            "DTM25": 1201.1
        }, 
        "easting": 578192.68, 
        "northing": 133569.761
    }, 
    {
        "dist": 12093.4, 
        "alts": {
            "DTM25": 1235.5
        }, 
        "easting": 578519.151, 
        "northing": 133519.761
    }, 
    {
        "dist": 12423.7, 
        "alts": {
            "DTM25": 1269.6
        }, 
        "easting": 578845.621, 
        "northing": 133469.761
    }, 
    {
        "dist": 12754.0, 
        "alts": {
            "DTM25": 1303.8
        }, 
        "easting": 579172.092, 
        "northing": 133419.761
    }, 
    {
        "dist": 13084.3, 
        "alts": {
            "DTM25": 1334.3
        }, 
        "easting": 579498.562, 
        "northing": 133369.761
    }, 
    {
        "dist": 13414.5, 
        "alts": {
            "DTM25": 1354.0
        }, 
        "easting": 579825.033, 
        "northing": 133319.761
    }, 
    {
        "dist": 13744.8, 
        "alts": {
            "DTM25": 1386.9
        }, 
        "easting": 580151.503, 
        "northing": 133269.761
    }, 
    {
        "dist": 14075.1, 
        "alts": {
            "DTM25": 1424.4
        }, 
        "easting": 580477.974, 
        "northing": 133219.761
    }, 
    {
        "dist": 14407.4, 
        "alts": {
            "DTM25": 1468.9
        }, 
        "easting": 580732.52, 
        "northing": 133006.124
    }, 
    {
        "dist": 14739.7, 
        "alts": {
            "DTM25": 1567.2
        }, 
        "easting": 580987.065, 
        "northing": 132792.488
    }, 
    {
        "dist": 15072.0, 
        "alts": {
            "DTM25": 1694.4
        }, 
        "easting": 581241.61, 
        "northing": 132578.852
    }, 
    {
        "dist": 15404.4, 
        "alts": {
            "DTM25": 1826.3
        }, 
        "easting": 581496.156, 
        "northing": 132365.215
    }, 
    {
        "dist": 15736.7, 
        "alts": {
            "DTM25": 1974.0
        }, 
        "easting": 581750.701, 
        "northing": 132151.579
    }, 
    {
        "dist": 16069.0, 
        "alts": {
            "DTM25": 2138.1
        }, 
        "easting": 582005.247, 
        "northing": 131937.943
    }, 
    {
        "dist": 16401.3, 
        "alts": {
            "DTM25": 2292.3
        }, 
        "easting": 582259.792, 
        "northing": 131724.306
    }, 
    {
        "dist": 16733.6, 
        "alts": {
            "DTM25": 2467.3
        }, 
        "easting": 582514.338, 
        "northing": 131510.67
    }, 
    {
        "dist": 17065.9, 
        "alts": {
            "DTM25": 2632.0
        }, 
        "easting": 582768.883, 
        "northing": 131297.033
    }, 
    {
        "dist": 17398.3, 
        "alts": {
            "DTM25": 2762.3
        }, 
        "easting": 583023.429, 
        "northing": 131083.397
    }, 
    {
        "dist": 17730.6, 
        "alts": {
            "DTM25": 2856.0
        }, 
        "easting": 583277.974, 
        "northing": 130869.761
    }, 
    {
        "dist": 18057.5, 
        "alts": {
            "DTM25": 2833.6
        }, 
        "easting": 583460.117, 
        "northing": 130598.332
    }, 
    {
        "dist": 18384.3, 
        "alts": {
            "DTM25": 2795.1
        }, 
        "easting": 583642.26, 
        "northing": 130326.904
    }, 
    {
        "dist": 18711.2, 
        "alts": {
            "DTM25": 2756.4
        }, 
        "easting": 583824.403, 
        "northing": 130055.475
    }, 
    {
        "dist": 19038.1, 
        "alts": {
            "DTM25": 2704.3
        }, 
        "easting": 584006.545, 
        "northing": 129784.046
    }, 
    {
        "dist": 19365.0, 
        "alts": {
            "DTM25": 2669.6
        }, 
        "easting": 584188.688, 
        "northing": 129512.618
    }, 
    {
        "dist": 19691.8, 
        "alts": {
            "DTM25": 2643.3
        }, 
        "easting": 584370.831, 
        "northing": 129241.189
    }, 
    {
        "dist": 20018.7, 
        "alts": {
            "DTM25": 2609.0
        }, 
        "easting": 584552.974, 
        "northing": 128969.761
    }, 
    {
        "dist": 20345.6, 
        "alts": {
            "DTM25": 2555.5
        }, 
        "easting": 584735.117, 
        "northing": 128698.332
    }, 
    {
        "dist": 20672.5, 
        "alts": {
            "DTM25": 2467.5
        }, 
        "easting": 584917.26, 
        "northing": 128426.904
    }, 
    {
        "dist": 20999.4, 
        "alts": {
            "DTM25": 2324.8
        }, 
        "easting": 585099.403, 
        "northing": 128155.475
    }, 
    {
        "dist": 21326.2, 
        "alts": {
            "DTM25": 2157.2
        }, 
        "easting": 585281.545, 
        "northing": 127884.046
    }, 
    {
        "dist": 21653.1, 
        "alts": {
            "DTM25": 1992.7
        }, 
        "easting": 585463.688, 
        "northing": 127612.618
    }, 
    {
        "dist": 21980.0, 
        "alts": {
            "DTM25": 1883.1
        }, 
        "easting": 585645.831, 
        "northing": 127341.189
    }, 
    {
        "dist": 22306.9, 
        "alts": {
            "DTM25": 1863.0
        }, 
        "easting": 585827.974, 
        "northing": 127069.761
    }, 
    {
        "dist": 22626.8, 
        "alts": {
            "DTM25": 1941.6
        }, 
        "easting": 586117.974, 
        "northing": 126934.761
    }, 
    {
        "dist": 22946.6, 
        "alts": {
            "DTM25": 2072.1
        }, 
        "easting": 586407.974, 
        "northing": 126799.761
    }, 
    {
        "dist": 23266.5, 
        "alts": {
            "DTM25": 2180.7
        }, 
        "easting": 586697.974, 
        "northing": 126664.761
    }, 
    {
        "dist": 23586.4, 
        "alts": {
            "DTM25": 2228.7
        }, 
        "easting": 586987.974, 
        "northing": 126529.761
    }, 
    {
        "dist": 23906.3, 
        "alts": {
            "DTM25": 2226.6
        }, 
        "easting": 587277.974, 
        "northing": 126394.761
    }, 
    {
        "dist": 24226.2, 
        "alts": {
            "DTM25": 2192.8
        }, 
        "easting": 587567.974, 
        "northing": 126259.761
    }, 
    {
        "dist": 24546.0, 
        "alts": {
            "DTM25": 2133.6
        }, 
        "easting": 587857.974, 
        "northing": 126124.761
    }, 
    {
        "dist": 24865.9, 
        "alts": {
            "DTM25": 2054.6
        }, 
        "easting": 588147.974, 
        "northing": 125989.761
    }, 
    {
        "dist": 25185.8, 
        "alts": {
            "DTM25": 1962.1
        }, 
        "easting": 588437.974, 
        "northing": 125854.761
    }, 
    {
        "dist": 25505.7, 
        "alts": {
            "DTM25": 1848.1
        }, 
        "easting": 588727.974, 
        "northing": 125719.761
    }, 
    {
        "dist": 25843.0, 
        "alts": {
            "DTM25": 1725.3
        }, 
        "easting": 588981.974, 
        "northing": 125497.761
    }, 
    {
        "dist": 26180.4, 
        "alts": {
            "DTM25": 1593.0
        }, 
        "easting": 589235.974, 
        "northing": 125275.761
    }, 
    {
        "dist": 26517.7, 
        "alts": {
            "DTM25": 1454.4
        }, 
        "easting": 589489.974, 
        "northing": 125053.761
    }, 
    {
        "dist": 26855.1, 
        "alts": {
            "DTM25": 1334.3
        }, 
        "easting": 589743.974, 
        "northing": 124831.761
    }, 
    {
        "dist": 27192.4, 
        "alts": {
            "DTM25": 1203.5
        }, 
        "easting": 589997.974, 
        "northing": 124609.761
    }, 
    {
        "dist": 27529.8, 
        "alts": {
            "DTM25": 1103.7
        }, 
        "easting": 590251.974, 
        "northing": 124387.761
    }, 
    {
        "dist": 27867.1, 
        "alts": {
            "DTM25": 1046.2
        }, 
        "easting": 590505.974, 
        "northing": 124165.761
    }, 
    {
        "dist": 28204.4, 
        "alts": {
            "DTM25": 993.2
        }, 
        "easting": 590759.974, 
        "northing": 123943.761
    }, 
    {
        "dist": 28541.8, 
        "alts": {
            "DTM25": 1012.6
        }, 
        "easting": 591013.974, 
        "northing": 123721.761
    }, 
    {
        "dist": 28879.1, 
        "alts": {
            "DTM25": 1077.7
        }, 
        "easting": 591267.974, 
        "northing": 123499.761
    }, 
    {
        "dist": 29216.5, 
        "alts": {
            "DTM25": 1094.5
        }, 
        "easting": 591521.974, 
        "northing": 123277.761
    }, 
    {
        "dist": 29553.8, 
        "alts": {
            "DTM25": 1082.7
        }, 
        "easting": 591775.974, 
        "northing": 123055.761
    }, 
    {
        "dist": 29891.2, 
        "alts": {
            "DTM25": 1051.0
        }, 
        "easting": 592029.974, 
        "northing": 122833.761
    }, 
    {
        "dist": 30228.5, 
        "alts": {
            "DTM25": 994.5
        }, 
        "easting": 592283.974, 
        "northing": 122611.761
    }, 
    {
        "dist": 30565.8, 
        "alts": {
            "DTM25": 930.4
        }, 
        "easting": 592537.974, 
        "northing": 122389.761
    }, 
    {
        "dist": 30903.2, 
        "alts": {
            "DTM25": 870.7
        }, 
        "easting": 592791.974, 
        "northing": 122167.761
    }, 
    {
        "dist": 31240.5, 
        "alts": {
            "DTM25": 819.1
        }, 
        "easting": 593045.974, 
        "northing": 121945.761
    }, 
    {
        "dist": 31577.9, 
        "alts": {
            "DTM25": 767.9
        }, 
        "easting": 593299.974, 
        "northing": 121723.761
    }, 
    {
        "dist": 31915.2, 
        "alts": {
            "DTM25": 718.0
        }, 
        "easting": 593553.974, 
        "northing": 121501.761
    }, 
    {
        "dist": 32252.5, 
        "alts": {
            "DTM25": 666.3
        }, 
        "easting": 593807.974, 
        "northing": 121279.761
    }, 
    {
        "dist": 32589.9, 
        "alts": {
            "DTM25": 611.1
        }, 
        "easting": 594061.974, 
        "northing": 121057.761
    }, 
    {
        "dist": 32927.2, 
        "alts": {
            "DTM25": 574.2
        }, 
        "easting": 594315.974, 
        "northing": 120835.761
    }, 
    {
        "dist": 33264.6, 
        "alts": {
            "DTM25": 554.3
        }, 
        "easting": 594569.974, 
        "northing": 120613.761
    }, 
    {
        "dist": 33601.9, 
        "alts": {
            "DTM25": 518.1
        }, 
        "easting": 594823.974, 
        "northing": 120391.761
    }, 
    {
        "dist": 33939.3, 
        "alts": {
            "DTM25": 505.1
        }, 
        "easting": 595077.974, 
        "northing": 120169.761
    }, 
    {
        "dist": 34271.7, 
        "alts": {
            "DTM25": 514.4
        }, 
        "easting": 595117.974, 
        "northing": 120499.761
    }, 
    {
        "dist": 34604.1, 
        "alts": {
            "DTM25": 528.8
        }, 
        "easting": 595157.974, 
        "northing": 120829.761
    }, 
    {
        "dist": 34936.5, 
        "alts": {
            "DTM25": 567.5
        }, 
        "easting": 595197.974, 
        "northing": 121159.761
    }, 
    {
        "dist": 35268.9, 
        "alts": {
            "DTM25": 646.0
        }, 
        "easting": 595237.974, 
        "northing": 121489.761
    }, 
    {
        "dist": 35601.3, 
        "alts": {
            "DTM25": 701.4
        }, 
        "easting": 595277.974, 
        "northing": 121819.761
    }, 
    {
        "dist": 35933.8, 
        "alts": {
            "DTM25": 754.1
        }, 
        "easting": 595317.974, 
        "northing": 122149.761
    }, 
    {
        "dist": 36266.2, 
        "alts": {
            "DTM25": 810.4
        }, 
        "easting": 595357.974, 
        "northing": 122479.761
    }, 
    {
        "dist": 36598.6, 
        "alts": {
            "DTM25": 843.3
        }, 
        "easting": 595397.974, 
        "northing": 122809.761
    }, 
    {
        "dist": 36931.0, 
        "alts": {
            "DTM25": 876.6
        }, 
        "easting": 595437.974, 
        "northing": 123139.761
    }, 
    {
        "dist": 37263.4, 
        "alts": {
            "DTM25": 931.2
        }, 
        "easting": 595477.974, 
        "northing": 123469.761
    }, 
    {
        "dist": 37595.8, 
        "alts": {
            "DTM25": 989.6
        }, 
        "easting": 595517.974, 
        "northing": 123799.761
    }, 
    {
        "dist": 37928.2, 
        "alts": {
            "DTM25": 1053.5
        }, 
        "easting": 595557.974, 
        "northing": 124129.761
    }, 
    {
        "dist": 38260.7, 
        "alts": {
            "DTM25": 1121.3
        }, 
        "easting": 595597.974, 
        "northing": 124459.761
    }, 
    {
        "dist": 38593.1, 
        "alts": {
            "DTM25": 1188.3
        }, 
        "easting": 595637.974, 
        "northing": 124789.761
    }, 
    {
        "dist": 38925.5, 
        "alts": {
            "DTM25": 1257.6
        }, 
        "easting": 595677.974, 
        "northing": 125119.761
    }, 
    {
        "dist": 39257.9, 
        "alts": {
            "DTM25": 1329.9
        }, 
        "easting": 595717.974, 
        "northing": 125449.761
    }, 
    {
        "dist": 39590.3, 
        "alts": {
            "DTM25": 1413.6
        }, 
        "easting": 595757.974, 
        "northing": 125779.761
    }, 
    {
        "dist": 39922.7, 
        "alts": {
            "DTM25": 1507.4
        }, 
        "easting": 595797.974, 
        "northing": 126109.761
    }, 
    {
        "dist": 40255.2, 
        "alts": {
            "DTM25": 1603.6
        }, 
        "easting": 595837.974, 
        "northing": 126439.761
    }, 
    {
        "dist": 40587.6, 
        "alts": {
            "DTM25": 1704.6
        }, 
        "easting": 595877.974, 
        "northing": 126769.761
    }, 
    {
        "dist": 40920.0, 
        "alts": {
            "DTM25": 1793.5
        }, 
        "easting": 595917.974, 
        "northing": 127099.761
    }, 
    {
        "dist": 41252.4, 
        "alts": {
            "DTM25": 1873.5
        }, 
        "easting": 595957.974, 
        "northing": 127429.761
    }, 
    {
        "dist": 41584.8, 
        "alts": {
            "DTM25": 1953.6
        }, 
        "easting": 595997.974, 
        "northing": 127759.761
    }, 
    {
        "dist": 41917.2, 
        "alts": {
            "DTM25": 2032.2
        }, 
        "easting": 596037.974, 
        "northing": 128089.761
    }, 
    {
        "dist": 42249.6, 
        "alts": {
            "DTM25": 2120.3
        }, 
        "easting": 596077.974, 
        "northing": 128419.761
    }, 
    {
        "dist": 42591.8, 
        "alts": {
            "DTM25": 2225.2
        }, 
        "easting": 596030.752, 
        "northing": 128758.65
    }, 
    {
        "dist": 42934.0, 
        "alts": {
            "DTM25": 2317.6
        }, 
        "easting": 595983.53, 
        "northing": 129097.538
    }, 
    {
        "dist": 43276.1, 
        "alts": {
            "DTM25": 2412.5
        }, 
        "easting": 595936.307, 
        "northing": 129436.427
    }, 
    {
        "dist": 43618.3, 
        "alts": {
            "DTM25": 2515.9
        }, 
        "easting": 595889.085, 
        "northing": 129775.316
    }, 
    {
        "dist": 43960.5, 
        "alts": {
            "DTM25": 2573.9
        }, 
        "easting": 595841.863, 
        "northing": 130114.205
    }, 
    {
        "dist": 44302.6, 
        "alts": {
            "DTM25": 2645.1
        }, 
        "easting": 595794.641, 
        "northing": 130453.094
    }, 
    {
        "dist": 44644.8, 
        "alts": {
            "DTM25": 2676.6
        }, 
        "easting": 595747.419, 
        "northing": 130791.983
    }, 
    {
        "dist": 44987.0, 
        "alts": {
            "DTM25": 2644.6
        }, 
        "easting": 595700.196, 
        "northing": 131130.872
    }, 
    {
        "dist": 45329.1, 
        "alts": {
            "DTM25": 2612.6
        }, 
        "easting": 595652.974, 
        "northing": 131469.761
    }, 
    {
        "dist": 45671.3, 
        "alts": {
            "DTM25": 2581.0
        }, 
        "easting": 595605.752, 
        "northing": 131808.65
    }, 
    {
        "dist": 46013.4, 
        "alts": {
            "DTM25": 2564.3
        }, 
        "easting": 595558.53, 
        "northing": 132147.538
    }, 
    {
        "dist": 46355.6, 
        "alts": {
            "DTM25": 2578.8
        }, 
        "easting": 595511.307, 
        "northing": 132486.427
    }, 
    {
        "dist": 46697.8, 
        "alts": {
            "DTM25": 2625.9
        }, 
        "easting": 595464.085, 
        "northing": 132825.316
    }, 
    {
        "dist": 47039.9, 
        "alts": {
            "DTM25": 2713.7
        }, 
        "easting": 595416.863, 
        "northing": 133164.205
    }, 
    {
        "dist": 47382.1, 
        "alts": {
            "DTM25": 2783.9
        }, 
        "easting": 595369.641, 
        "northing": 133503.094
    }, 
    {
        "dist": 47724.3, 
        "alts": {
            "DTM25": 2842.7
        }, 
        "easting": 595322.419, 
        "northing": 133841.983
    }, 
    {
        "dist": 48066.4, 
        "alts": {
            "DTM25": 2879.5
        }, 
        "easting": 595275.196, 
        "northing": 134180.872
    }, 
    {
        "dist": 48408.6, 
        "alts": {
            "DTM25": 2876.2
        }, 
        "easting": 595227.974, 
        "northing": 134519.761
    }, 
    {
        "dist": 48736.5, 
        "alts": {
            "DTM25": 2844.0
        }, 
        "easting": 595511.857, 
        "northing": 134683.84
    }, 
    {
        "dist": 49064.4, 
        "alts": {
            "DTM25": 2817.6
        }, 
        "easting": 595795.74, 
        "northing": 134847.92
    }, 
    {
        "dist": 49392.3, 
        "alts": {
            "DTM25": 2793.3
        }, 
        "easting": 596079.623, 
        "northing": 135012.0
    }, 
    {
        "dist": 49720.1, 
        "alts": {
            "DTM25": 2761.7
        }, 
        "easting": 596363.506, 
        "northing": 135176.08
    }, 
    {
        "dist": 50048.0, 
        "alts": {
            "DTM25": 2771.6
        }, 
        "easting": 596647.389, 
        "northing": 135340.16
    }, 
    {
        "dist": 50375.9, 
        "alts": {
            "DTM25": 2741.1
        }, 
        "easting": 596931.272, 
        "northing": 135504.239
    }, 
    {
        "dist": 50703.8, 
        "alts": {
            "DTM25": 2710.4
        }, 
        "easting": 597215.155, 
        "northing": 135668.319
    }, 
    {
        "dist": 51031.7, 
        "alts": {
            "DTM25": 2695.9
        }, 
        "easting": 597499.038, 
        "northing": 135832.399
    }, 
    {
        "dist": 51359.6, 
        "alts": {
            "DTM25": 2653.0
        }, 
        "easting": 597782.921, 
        "northing": 135996.479
    }, 
    {
        "dist": 51687.5, 
        "alts": {
            "DTM25": 2623.9
        }, 
        "easting": 598066.804, 
        "northing": 136160.558
    }, 
    {
        "dist": 52015.4, 
        "alts": {
            "DTM25": 2632.8
        }, 
        "easting": 598350.687, 
        "northing": 136324.638
    }, 
    {
        "dist": 52343.3, 
        "alts": {
            "DTM25": 2607.9
        }, 
        "easting": 598634.57, 
        "northing": 136488.718
    }, 
    {
        "dist": 52671.2, 
        "alts": {
            "DTM25": 2583.4
        }, 
        "easting": 598918.453, 
        "northing": 136652.798
    }, 
    {
        "dist": 52999.0, 
        "alts": {
            "DTM25": 2569.3
        }, 
        "easting": 599202.335, 
        "northing": 136816.878
    }, 
    {
        "dist": 53326.9, 
        "alts": {
            "DTM25": 2549.0
        }, 
        "easting": 599486.218, 
        "northing": 136980.957
    }, 
    {
        "dist": 53654.8, 
        "alts": {
            "DTM25": 2530.0
        }, 
        "easting": 599770.101, 
        "northing": 137145.037
    }, 
    {
        "dist": 53986.6, 
        "alts": {
            "DTM25": 2498.4
        }, 
        "easting": 599954.717, 
        "northing": 136869.396
    }, 
    {
        "dist": 54318.3, 
        "alts": {
            "DTM25": 2492.0
        }, 
        "easting": 600139.332, 
        "northing": 136593.755
    }, 
    {
        "dist": 54650.1, 
        "alts": {
            "DTM25": 2510.8
        }, 
        "easting": 600323.948, 
        "northing": 136318.114
    }, 
    {
        "dist": 54981.8, 
        "alts": {
            "DTM25": 2548.3
        }, 
        "easting": 600508.563, 
        "northing": 136042.473
    }, 
    {
        "dist": 55313.6, 
        "alts": {
            "DTM25": 2600.9
        }, 
        "easting": 600693.178, 
        "northing": 135766.832
    }, 
    {
        "dist": 55645.3, 
        "alts": {
            "DTM25": 2599.8
        }, 
        "easting": 600877.794, 
        "northing": 135491.191
    }, 
    {
        "dist": 55977.1, 
        "alts": {
            "DTM25": 2566.2
        }, 
        "easting": 601062.409, 
        "northing": 135215.55
    }, 
    {
        "dist": 56308.9, 
        "alts": {
            "DTM25": 2533.2
        }, 
        "easting": 601247.024, 
        "northing": 134939.909
    }, 
    {
        "dist": 56640.6, 
        "alts": {
            "DTM25": 2491.1
        }, 
        "easting": 601431.64, 
        "northing": 134664.268
    }, 
    {
        "dist": 56972.4, 
        "alts": {
            "DTM25": 2458.2
        }, 
        "easting": 601616.255, 
        "northing": 134388.627
    }, 
    {
        "dist": 57304.1, 
        "alts": {
            "DTM25": 2417.4
        }, 
        "easting": 601800.871, 
        "northing": 134112.986
    }, 
    {
        "dist": 57635.9, 
        "alts": {
            "DTM25": 2344.9
        }, 
        "easting": 601985.486, 
        "northing": 133837.345
    }, 
    {
        "dist": 57967.6, 
        "alts": {
            "DTM25": 2238.4
        }, 
        "easting": 602170.101, 
        "northing": 133561.704
    }, 
    {
        "dist": 58299.4, 
        "alts": {
            "DTM25": 2122.6
        }, 
        "easting": 602354.717, 
        "northing": 133286.063
    }, 
    {
        "dist": 58631.1, 
        "alts": {
            "DTM25": 2056.7
        }, 
        "easting": 602539.332, 
        "northing": 133010.422
    }, 
    {
        "dist": 58962.9, 
        "alts": {
            "DTM25": 2038.6
        }, 
        "easting": 602723.948, 
        "northing": 132734.781
    }, 
    {
        "dist": 59294.6, 
        "alts": {
            "DTM25": 2071.7
        }, 
        "easting": 602908.563, 
        "northing": 132459.14
    }, 
    {
        "dist": 59626.4, 
        "alts": {
            "DTM25": 2142.5
        }, 
        "easting": 603093.178, 
        "northing": 132183.499
    }, 
    {
        "dist": 59958.1, 
        "alts": {
            "DTM25": 2153.4
        }, 
        "easting": 603277.794, 
        "northing": 131907.858
    }, 
    {
        "dist": 60289.9, 
        "alts": {
            "DTM25": 2103.0
        }, 
        "easting": 603462.409, 
        "northing": 131632.217
    }, 
    {
        "dist": 60621.7, 
        "alts": {
            "DTM25": 2030.9
        }, 
        "easting": 603647.024, 
        "northing": 131356.576
    }, 
    {
        "dist": 60953.4, 
        "alts": {
            "DTM25": 1932.2
        }, 
        "easting": 603831.64, 
        "northing": 131080.935
    }, 
    {
        "dist": 61285.2, 
        "alts": {
            "DTM25": 1822.9
        }, 
        "easting": 604016.255, 
        "northing": 130805.294
    }, 
    {
        "dist": 61616.9, 
        "alts": {
            "DTM25": 1726.8
        }, 
        "easting": 604200.871, 
        "northing": 130529.652
    }, 
    {
        "dist": 61948.7, 
        "alts": {
            "DTM25": 1635.3
        }, 
        "easting": 604385.486, 
        "northing": 130254.011
    }, 
    {
        "dist": 62280.4, 
        "alts": {
            "DTM25": 1548.4
        }, 
        "easting": 604570.101, 
        "northing": 129978.37
    }, 
    {
        "dist": 62612.2, 
        "alts": {
            "DTM25": 1475.8
        }, 
        "easting": 604754.717, 
        "northing": 129702.729
    }, 
    {
        "dist": 62943.9, 
        "alts": {
            "DTM25": 1395.1
        }, 
        "easting": 604939.332, 
        "northing": 129427.088
    }, 
    {
        "dist": 63275.7, 
        "alts": {
            "DTM25": 1311.7
        }, 
        "easting": 605123.948, 
        "northing": 129151.447
    }, 
    {
        "dist": 63607.4, 
        "alts": {
            "DTM25": 1222.7
        }, 
        "easting": 605308.563, 
        "northing": 128875.806
    }, 
    {
        "dist": 63939.2, 
        "alts": {
            "DTM25": 1124.3
        }, 
        "easting": 605493.178, 
        "northing": 128600.165
    }, 
    {
        "dist": 64271.0, 
        "alts": {
            "DTM25": 1025.7
        }, 
        "easting": 605677.794, 
        "northing": 128324.524
    }, 
    {
        "dist": 64602.7, 
        "alts": {
            "DTM25": 926.0
        }, 
        "easting": 605862.409, 
        "northing": 128048.883
    }, 
    {
        "dist": 64934.5, 
        "alts": {
            "DTM25": 836.4
        }, 
        "easting": 606047.024, 
        "northing": 127773.242
    }, 
    {
        "dist": 65266.2, 
        "alts": {
            "DTM25": 751.7
        }, 
        "easting": 606231.64, 
        "northing": 127497.601
    }, 
    {
        "dist": 65598.0, 
        "alts": {
            "DTM25": 673.0
        }, 
        "easting": 606416.255, 
        "northing": 127221.96
    }, 
    {
        "dist": 65929.7, 
        "alts": {
            "DTM25": 620.2
        }, 
        "easting": 606600.871, 
        "northing": 126946.319
    }, 
    {
        "dist": 66261.5, 
        "alts": {
            "DTM25": 581.2
        }, 
        "easting": 606785.486, 
        "northing": 126670.678
    }, 
    {
        "dist": 66593.2, 
        "alts": {
            "DTM25": 554.6
        }, 
        "easting": 606970.101, 
        "northing": 126395.037
    }
]
