[
    {
        "dist": 0.0, 
        "alts": {
            "DTM25": 1930.9
        }, 
        "easting": 616266.952, 
        "northing": 145239.55
    }, 
    {
        "dist": 41.8, 
        "alts": {
            "DTM25": 1932.9
        }, 
        "easting": 616246.952, 
        "northing": 145202.883
    }, 
    {
        "dist": 83.5, 
        "alts": {
            "DTM25": 1934.3
        }, 
        "easting": 616226.952, 
        "northing": 145166.216
    }, 
    {
        "dist": 125.3, 
        "alts": {
            "DTM25": 1934.7
        }, 
        "easting": 616206.952, 
        "northing": 145129.55
    }, 
    {
        "dist": 167.1, 
        "alts": {
            "DTM25": 1935.1
        }, 
        "easting": 616186.952, 
        "northing": 145092.883
    }, 
    {
        "dist": 208.8, 
        "alts": {
            "DTM25": 1934.1
        }, 
        "easting": 616166.952, 
        "northing": 145056.216
    }, 
    {
        "dist": 250.6, 
        "alts": {
            "DTM25": 1931.8
        }, 
        "easting": 616146.952, 
        "northing": 145019.55
    }, 
    {
        "dist": 293.5, 
        "alts": {
            "DTM25": 1931.0
        }, 
        "easting": 616108.952, 
        "northing": 144999.55
    }, 
    {
        "dist": 336.5, 
        "alts": {
            "DTM25": 1929.7
        }, 
        "easting": 616070.952, 
        "northing": 144979.55
    }, 
    {
        "dist": 379.4, 
        "alts": {
            "DTM25": 1927.7
        }, 
        "easting": 616032.952, 
        "northing": 144959.55
    }, 
    {
        "dist": 422.4, 
        "alts": {
            "DTM25": 1926.0
        }, 
        "easting": 615994.952, 
        "northing": 144939.55
    }, 
    {
        "dist": 465.3, 
        "alts": {
            "DTM25": 1924.8
        }, 
        "easting": 615956.952, 
        "northing": 144919.55
    }, 
    {
        "dist": 505.4, 
        "alts": {
            "DTM25": 1920.7
        }, 
        "easting": 615960.285, 
        "northing": 144879.55
    }, 
    {
        "dist": 545.6, 
        "alts": {
            "DTM25": 1917.0
        }, 
        "easting": 615963.618, 
        "northing": 144839.55
    }, 
    {
        "dist": 585.7, 
        "alts": {
            "DTM25": 1913.7
        }, 
        "easting": 615966.952, 
        "northing": 144799.55
    }, 
    {
        "dist": 625.9, 
        "alts": {
            "DTM25": 1906.8
        }, 
        "easting": 615970.285, 
        "northing": 144759.55
    }, 
    {
        "dist": 666.0, 
        "alts": {
            "DTM25": 1900.3
        }, 
        "easting": 615973.618, 
        "northing": 144719.55
    }, 
    {
        "dist": 706.1, 
        "alts": {
            "DTM25": 1894.1
        }, 
        "easting": 615976.952, 
        "northing": 144679.55
    }, 
    {
        "dist": 745.3, 
        "alts": {
            "DTM25": 1886.9
        }, 
        "easting": 615952.952, 
        "northing": 144648.55
    }, 
    {
        "dist": 784.5, 
        "alts": {
            "DTM25": 1882.3
        }, 
        "easting": 615928.952, 
        "northing": 144617.55
    }, 
    {
        "dist": 823.8, 
        "alts": {
            "DTM25": 1880.1
        }, 
        "easting": 615904.952, 
        "northing": 144586.55
    }, 
    {
        "dist": 863.0, 
        "alts": {
            "DTM25": 1879.3
        }, 
        "easting": 615880.952, 
        "northing": 144555.55
    }, 
    {
        "dist": 902.2, 
        "alts": {
            "DTM25": 1880.7
        }, 
        "easting": 615856.952, 
        "northing": 144524.55
    }, 
    {
        "dist": 941.4, 
        "alts": {
            "DTM25": 1882.5
        }, 
        "easting": 615832.952, 
        "northing": 144493.55
    }, 
    {
        "dist": 980.6, 
        "alts": {
            "DTM25": 1884.3
        }, 
        "easting": 615808.952, 
        "northing": 144462.55
    }, 
    {
        "dist": 1019.8, 
        "alts": {
            "DTM25": 1886.0
        }, 
        "easting": 615784.952, 
        "northing": 144431.55
    }, 
    {
        "dist": 1059.0, 
        "alts": {
            "DTM25": 1887.1
        }, 
        "easting": 615760.952, 
        "northing": 144400.55
    }, 
    {
        "dist": 1098.2, 
        "alts": {
            "DTM25": 1887.4
        }, 
        "easting": 615736.952, 
        "northing": 144369.55
    }, 
    {
        "dist": 1141.3, 
        "alts": {
            "DTM25": 1887.2
        }, 
        "easting": 615729.452, 
        "northing": 144327.05
    }, 
    {
        "dist": 1184.5, 
        "alts": {
            "DTM25": 1887.0
        }, 
        "easting": 615721.952, 
        "northing": 144284.55
    }, 
    {
        "dist": 1227.7, 
        "alts": {
            "DTM25": 1886.1
        }, 
        "easting": 615714.452, 
        "northing": 144242.05
    }, 
    {
        "dist": 1270.8, 
        "alts": {
            "DTM25": 1884.8
        }, 
        "easting": 615706.952, 
        "northing": 144199.55
    }, 
    {
        "dist": 1313.8, 
        "alts": {
            "DTM25": 1883.1
        }, 
        "easting": 615713.202, 
        "northing": 144157.05
    }, 
    {
        "dist": 1356.7, 
        "alts": {
            "DTM25": 1881.7
        }, 
        "easting": 615719.452, 
        "northing": 144114.55
    }, 
    {
        "dist": 1399.7, 
        "alts": {
            "DTM25": 1880.1
        }, 
        "easting": 615725.702, 
        "northing": 144072.05
    }, 
    {
        "dist": 1442.6, 
        "alts": {
            "DTM25": 1878.9
        }, 
        "easting": 615731.952, 
        "northing": 144029.55
    }, 
    {
        "dist": 1485.6, 
        "alts": {
            "DTM25": 1877.8
        }, 
        "easting": 615738.202, 
        "northing": 143987.05
    }, 
    {
        "dist": 1528.6, 
        "alts": {
            "DTM25": 1876.2
        }, 
        "easting": 615744.452, 
        "northing": 143944.55
    }, 
    {
        "dist": 1571.5, 
        "alts": {
            "DTM25": 1875.5
        }, 
        "easting": 615750.702, 
        "northing": 143902.05
    }, 
    {
        "dist": 1614.5, 
        "alts": {
            "DTM25": 1873.6
        }, 
        "easting": 615756.952, 
        "northing": 143859.55
    }, 
    {
        "dist": 1654.9, 
        "alts": {
            "DTM25": 1873.3
        }, 
        "easting": 615730.798, 
        "northing": 143828.78
    }, 
    {
        "dist": 1695.2, 
        "alts": {
            "DTM25": 1874.4
        }, 
        "easting": 615704.644, 
        "northing": 143798.011
    }, 
    {
        "dist": 1735.6, 
        "alts": {
            "DTM25": 1874.9
        }, 
        "easting": 615678.49, 
        "northing": 143767.242
    }, 
    {
        "dist": 1776.0, 
        "alts": {
            "DTM25": 1876.3
        }, 
        "easting": 615652.336, 
        "northing": 143736.473
    }, 
    {
        "dist": 1816.4, 
        "alts": {
            "DTM25": 1878.0
        }, 
        "easting": 615626.182, 
        "northing": 143705.703
    }, 
    {
        "dist": 1856.8, 
        "alts": {
            "DTM25": 1879.4
        }, 
        "easting": 615600.028, 
        "northing": 143674.934
    }, 
    {
        "dist": 1897.1, 
        "alts": {
            "DTM25": 1881.1
        }, 
        "easting": 615573.875, 
        "northing": 143644.165
    }, 
    {
        "dist": 1937.5, 
        "alts": {
            "DTM25": 1882.7
        }, 
        "easting": 615547.721, 
        "northing": 143613.396
    }, 
    {
        "dist": 1977.9, 
        "alts": {
            "DTM25": 1884.4
        }, 
        "easting": 615521.567, 
        "northing": 143582.627
    }, 
    {
        "dist": 2018.3, 
        "alts": {
            "DTM25": 1886.1
        }, 
        "easting": 615495.413, 
        "northing": 143551.857
    }, 
    {
        "dist": 2058.7, 
        "alts": {
            "DTM25": 1887.8
        }, 
        "easting": 615469.259, 
        "northing": 143521.088
    }, 
    {
        "dist": 2099.1, 
        "alts": {
            "DTM25": 1889.4
        }, 
        "easting": 615443.105, 
        "northing": 143490.319
    }, 
    {
        "dist": 2139.4, 
        "alts": {
            "DTM25": 1891.2
        }, 
        "easting": 615416.952, 
        "northing": 143459.55
    }, 
    {
        "dist": 2179.9, 
        "alts": {
            "DTM25": 1892.9
        }, 
        "easting": 615394.952, 
        "northing": 143425.55
    }, 
    {
        "dist": 2220.4, 
        "alts": {
            "DTM25": 1894.6
        }, 
        "easting": 615372.952, 
        "northing": 143391.55
    }, 
    {
        "dist": 2260.9, 
        "alts": {
            "DTM25": 1896.2
        }, 
        "easting": 615350.952, 
        "northing": 143357.55
    }, 
    {
        "dist": 2301.4, 
        "alts": {
            "DTM25": 1897.7
        }, 
        "easting": 615328.952, 
        "northing": 143323.55
    }, 
    {
        "dist": 2341.9, 
        "alts": {
            "DTM25": 1899.0
        }, 
        "easting": 615306.952, 
        "northing": 143289.55
    }, 
    {
        "dist": 2384.2, 
        "alts": {
            "DTM25": 1900.3
        }, 
        "easting": 615296.952, 
        "northing": 143248.438
    }, 
    {
        "dist": 2426.6, 
        "alts": {
            "DTM25": 1901.7
        }, 
        "easting": 615286.952, 
        "northing": 143207.327
    }, 
    {
        "dist": 2468.9, 
        "alts": {
            "DTM25": 1904.0
        }, 
        "easting": 615276.952, 
        "northing": 143166.216
    }, 
    {
        "dist": 2511.2, 
        "alts": {
            "DTM25": 1907.5
        }, 
        "easting": 615266.952, 
        "northing": 143125.105
    }, 
    {
        "dist": 2553.5, 
        "alts": {
            "DTM25": 1912.7
        }, 
        "easting": 615256.952, 
        "northing": 143083.994
    }, 
    {
        "dist": 2595.8, 
        "alts": {
            "DTM25": 1919.9
        }, 
        "easting": 615246.952, 
        "northing": 143042.883
    }, 
    {
        "dist": 2638.1, 
        "alts": {
            "DTM25": 1927.3
        }, 
        "easting": 615236.952, 
        "northing": 143001.772
    }, 
    {
        "dist": 2680.4, 
        "alts": {
            "DTM25": 1933.3
        }, 
        "easting": 615226.952, 
        "northing": 142960.661
    }, 
    {
        "dist": 2722.7, 
        "alts": {
            "DTM25": 1937.9
        }, 
        "easting": 615216.952, 
        "northing": 142919.55
    }, 
    {
        "dist": 2765.5, 
        "alts": {
            "DTM25": 1940.6
        }, 
        "easting": 615182.952, 
        "northing": 142893.55
    }, 
    {
        "dist": 2808.3, 
        "alts": {
            "DTM25": 1941.7
        }, 
        "easting": 615148.952, 
        "northing": 142867.55
    }, 
    {
        "dist": 2851.1, 
        "alts": {
            "DTM25": 1942.2
        }, 
        "easting": 615114.952, 
        "northing": 142841.55
    }, 
    {
        "dist": 2893.9, 
        "alts": {
            "DTM25": 1943.4
        }, 
        "easting": 615080.952, 
        "northing": 142815.55
    }, 
    {
        "dist": 2936.7, 
        "alts": {
            "DTM25": 1946.0
        }, 
        "easting": 615046.952, 
        "northing": 142789.55
    }, 
    {
        "dist": 2979.5, 
        "alts": {
            "DTM25": 1952.0
        }, 
        "easting": 615012.952, 
        "northing": 142763.55
    }, 
    {
        "dist": 3022.3, 
        "alts": {
            "DTM25": 1962.0
        }, 
        "easting": 614978.952, 
        "northing": 142737.55
    }, 
    {
        "dist": 3065.1, 
        "alts": {
            "DTM25": 1972.0
        }, 
        "easting": 614944.952, 
        "northing": 142711.55
    }, 
    {
        "dist": 3107.9, 
        "alts": {
            "DTM25": 1983.0
        }, 
        "easting": 614910.952, 
        "northing": 142685.55
    }, 
    {
        "dist": 3150.7, 
        "alts": {
            "DTM25": 1995.0
        }, 
        "easting": 614876.952, 
        "northing": 142659.55
    }, 
    {
        "dist": 3194.1, 
        "alts": {
            "DTM25": 2005.3
        }, 
        "easting": 614836.952, 
        "northing": 142642.883
    }, 
    {
        "dist": 3237.4, 
        "alts": {
            "DTM25": 2015.5
        }, 
        "easting": 614796.952, 
        "northing": 142626.216
    }, 
    {
        "dist": 3280.7, 
        "alts": {
            "DTM25": 2026.4
        }, 
        "easting": 614756.952, 
        "northing": 142609.55
    }, 
    {
        "dist": 3322.8, 
        "alts": {
            "DTM25": 2034.6
        }, 
        "easting": 614758.952, 
        "northing": 142567.55
    }, 
    {
        "dist": 3364.8, 
        "alts": {
            "DTM25": 2042.3
        }, 
        "easting": 614760.952, 
        "northing": 142525.55
    }, 
    {
        "dist": 3406.9, 
        "alts": {
            "DTM25": 2049.5
        }, 
        "easting": 614762.952, 
        "northing": 142483.55
    }, 
    {
        "dist": 3448.9, 
        "alts": {
            "DTM25": 2054.7
        }, 
        "easting": 614764.952, 
        "northing": 142441.55
    }, 
    {
        "dist": 3491.0, 
        "alts": {
            "DTM25": 2058.3
        }, 
        "easting": 614766.952, 
        "northing": 142399.55
    }, 
    {
        "dist": 3534.3, 
        "alts": {
            "DTM25": 2060.9
        }, 
        "easting": 614723.618, 
        "northing": 142397.883
    }, 
    {
        "dist": 3577.7, 
        "alts": {
            "DTM25": 2062.1
        }, 
        "easting": 614680.285, 
        "northing": 142396.216
    }, 
    {
        "dist": 3621.1, 
        "alts": {
            "DTM25": 2061.6
        }, 
        "easting": 614636.952, 
        "northing": 142394.55
    }, 
    {
        "dist": 3664.4, 
        "alts": {
            "DTM25": 2061.9
        }, 
        "easting": 614593.618, 
        "northing": 142392.883
    }, 
    {
        "dist": 3707.8, 
        "alts": {
            "DTM25": 2062.9
        }, 
        "easting": 614550.285, 
        "northing": 142391.216
    }, 
    {
        "dist": 3751.2, 
        "alts": {
            "DTM25": 2065.2
        }, 
        "easting": 614506.952, 
        "northing": 142389.55
    }, 
    {
        "dist": 3791.4, 
        "alts": {
            "DTM25": 2069.0
        }, 
        "easting": 614467.952, 
        "northing": 142379.55
    }, 
    {
        "dist": 3831.7, 
        "alts": {
            "DTM25": 2072.1
        }, 
        "easting": 614428.952, 
        "northing": 142369.55
    }, 
    {
        "dist": 3872.0, 
        "alts": {
            "DTM25": 2074.3
        }, 
        "easting": 614389.952, 
        "northing": 142359.55
    }, 
    {
        "dist": 3912.2, 
        "alts": {
            "DTM25": 2074.8
        }, 
        "easting": 614350.952, 
        "northing": 142349.55
    }, 
    {
        "dist": 3952.5, 
        "alts": {
            "DTM25": 2072.3
        }, 
        "easting": 614311.952, 
        "northing": 142339.55
    }, 
    {
        "dist": 3992.7, 
        "alts": {
            "DTM25": 2067.3
        }, 
        "easting": 614272.952, 
        "northing": 142329.55
    }, 
    {
        "dist": 4033.0, 
        "alts": {
            "DTM25": 2061.4
        }, 
        "easting": 614233.952, 
        "northing": 142319.55
    }, 
    {
        "dist": 4073.3, 
        "alts": {
            "DTM25": 2055.1
        }, 
        "easting": 614194.952, 
        "northing": 142309.55
    }, 
    {
        "dist": 4113.5, 
        "alts": {
            "DTM25": 2051.2
        }, 
        "easting": 614155.952, 
        "northing": 142299.55
    }, 
    {
        "dist": 4153.8, 
        "alts": {
            "DTM25": 2051.5
        }, 
        "easting": 614116.952, 
        "northing": 142289.55
    }, 
    {
        "dist": 4194.2, 
        "alts": {
            "DTM25": 2051.3
        }, 
        "easting": 614104.809, 
        "northing": 142250.978
    }, 
    {
        "dist": 4234.7, 
        "alts": {
            "DTM25": 2052.9
        }, 
        "easting": 614092.666, 
        "northing": 142212.407
    }, 
    {
        "dist": 4275.1, 
        "alts": {
            "DTM25": 2054.8
        }, 
        "easting": 614080.523, 
        "northing": 142173.835
    }, 
    {
        "dist": 4315.5, 
        "alts": {
            "DTM25": 2055.2
        }, 
        "easting": 614068.38, 
        "northing": 142135.264
    }, 
    {
        "dist": 4356.0, 
        "alts": {
            "DTM25": 2058.4
        }, 
        "easting": 614056.237, 
        "northing": 142096.692
    }, 
    {
        "dist": 4396.4, 
        "alts": {
            "DTM25": 2061.7
        }, 
        "easting": 614044.094, 
        "northing": 142058.121
    }, 
    {
        "dist": 4436.8, 
        "alts": {
            "DTM25": 2066.5
        }, 
        "easting": 614031.952, 
        "northing": 142019.55
    }, 
    {
        "dist": 4477.3, 
        "alts": {
            "DTM25": 2072.1
        }, 
        "easting": 614019.809, 
        "northing": 141980.978
    }, 
    {
        "dist": 4517.7, 
        "alts": {
            "DTM25": 2078.2
        }, 
        "easting": 614007.666, 
        "northing": 141942.407
    }, 
    {
        "dist": 4558.2, 
        "alts": {
            "DTM25": 2084.5
        }, 
        "easting": 613995.523, 
        "northing": 141903.835
    }, 
    {
        "dist": 4598.6, 
        "alts": {
            "DTM25": 2089.7
        }, 
        "easting": 613983.38, 
        "northing": 141865.264
    }, 
    {
        "dist": 4639.0, 
        "alts": {
            "DTM25": 2095.5
        }, 
        "easting": 613971.237, 
        "northing": 141826.692
    }, 
    {
        "dist": 4679.5, 
        "alts": {
            "DTM25": 2101.9
        }, 
        "easting": 613959.094, 
        "northing": 141788.121
    }, 
    {
        "dist": 4719.9, 
        "alts": {
            "DTM25": 2107.8
        }, 
        "easting": 613946.952, 
        "northing": 141749.55
    }, 
    {
        "dist": 4760.2, 
        "alts": {
            "DTM25": 2111.9
        }, 
        "easting": 613962.666, 
        "northing": 141712.407
    }, 
    {
        "dist": 4800.6, 
        "alts": {
            "DTM25": 2115.9
        }, 
        "easting": 613978.38, 
        "northing": 141675.264
    }, 
    {
        "dist": 4840.9, 
        "alts": {
            "DTM25": 2120.5
        }, 
        "easting": 613994.094, 
        "northing": 141638.121
    }, 
    {
        "dist": 4881.2, 
        "alts": {
            "DTM25": 2125.8
        }, 
        "easting": 614009.809, 
        "northing": 141600.978
    }, 
    {
        "dist": 4921.6, 
        "alts": {
            "DTM25": 2133.0
        }, 
        "easting": 614025.523, 
        "northing": 141563.835
    }, 
    {
        "dist": 4961.9, 
        "alts": {
            "DTM25": 2142.3
        }, 
        "easting": 614041.237, 
        "northing": 141526.692
    }, 
    {
        "dist": 5002.2, 
        "alts": {
            "DTM25": 2150.8
        }, 
        "easting": 614056.952, 
        "northing": 141489.55
    }, 
    {
        "dist": 5042.6, 
        "alts": {
            "DTM25": 2158.6
        }, 
        "easting": 614072.666, 
        "northing": 141452.407
    }, 
    {
        "dist": 5082.9, 
        "alts": {
            "DTM25": 2166.9
        }, 
        "easting": 614088.38, 
        "northing": 141415.264
    }, 
    {
        "dist": 5123.2, 
        "alts": {
            "DTM25": 2172.4
        }, 
        "easting": 614104.094, 
        "northing": 141378.121
    }, 
    {
        "dist": 5163.5, 
        "alts": {
            "DTM25": 2177.3
        }, 
        "easting": 614119.809, 
        "northing": 141340.978
    }, 
    {
        "dist": 5203.9, 
        "alts": {
            "DTM25": 2181.1
        }, 
        "easting": 614135.523, 
        "northing": 141303.835
    }, 
    {
        "dist": 5244.2, 
        "alts": {
            "DTM25": 2183.5
        }, 
        "easting": 614151.237, 
        "northing": 141266.692
    }, 
    {
        "dist": 5284.5, 
        "alts": {
            "DTM25": 2187.2
        }, 
        "easting": 614166.952, 
        "northing": 141229.55
    }, 
    {
        "dist": 5325.2, 
        "alts": {
            "DTM25": 2191.3
        }, 
        "easting": 614174.285, 
        "northing": 141189.55
    }, 
    {
        "dist": 5365.9, 
        "alts": {
            "DTM25": 2196.2
        }, 
        "easting": 614181.618, 
        "northing": 141149.55
    }, 
    {
        "dist": 5406.5, 
        "alts": {
            "DTM25": 2202.5
        }, 
        "easting": 614188.952, 
        "northing": 141109.55
    }, 
    {
        "dist": 5447.2, 
        "alts": {
            "DTM25": 2207.7
        }, 
        "easting": 614196.285, 
        "northing": 141069.55
    }, 
    {
        "dist": 5487.9, 
        "alts": {
            "DTM25": 2212.2
        }, 
        "easting": 614203.618, 
        "northing": 141029.55
    }, 
    {
        "dist": 5528.5, 
        "alts": {
            "DTM25": 2214.0
        }, 
        "easting": 614210.952, 
        "northing": 140989.55
    }, 
    {
        "dist": 5569.2, 
        "alts": {
            "DTM25": 2213.9
        }, 
        "easting": 614218.285, 
        "northing": 140949.55
    }, 
    {
        "dist": 5609.9, 
        "alts": {
            "DTM25": 2211.9
        }, 
        "easting": 614225.618, 
        "northing": 140909.55
    }, 
    {
        "dist": 5650.5, 
        "alts": {
            "DTM25": 2209.7
        }, 
        "easting": 614232.952, 
        "northing": 140869.55
    }, 
    {
        "dist": 5691.2, 
        "alts": {
            "DTM25": 2209.3
        }, 
        "easting": 614240.285, 
        "northing": 140829.55
    }, 
    {
        "dist": 5731.9, 
        "alts": {
            "DTM25": 2208.1
        }, 
        "easting": 614247.618, 
        "northing": 140789.55
    }, 
    {
        "dist": 5772.5, 
        "alts": {
            "DTM25": 2209.1
        }, 
        "easting": 614254.952, 
        "northing": 140749.55
    }, 
    {
        "dist": 5813.2, 
        "alts": {
            "DTM25": 2211.1
        }, 
        "easting": 614262.285, 
        "northing": 140709.55
    }, 
    {
        "dist": 5853.9, 
        "alts": {
            "DTM25": 2213.9
        }, 
        "easting": 614269.618, 
        "northing": 140669.55
    }, 
    {
        "dist": 5894.5, 
        "alts": {
            "DTM25": 2216.8
        }, 
        "easting": 614276.952, 
        "northing": 140629.55
    }, 
    {
        "dist": 5934.8, 
        "alts": {
            "DTM25": 2217.6
        }, 
        "easting": 614268.952, 
        "northing": 140590.05
    }, 
    {
        "dist": 5975.1, 
        "alts": {
            "DTM25": 2217.9
        }, 
        "easting": 614260.952, 
        "northing": 140550.55
    }, 
    {
        "dist": 6015.4, 
        "alts": {
            "DTM25": 2217.6
        }, 
        "easting": 614252.952, 
        "northing": 140511.05
    }, 
    {
        "dist": 6055.7, 
        "alts": {
            "DTM25": 2216.5
        }, 
        "easting": 614244.952, 
        "northing": 140471.55
    }, 
    {
        "dist": 6096.0, 
        "alts": {
            "DTM25": 2215.5
        }, 
        "easting": 614236.952, 
        "northing": 140432.05
    }, 
    {
        "dist": 6136.3, 
        "alts": {
            "DTM25": 2214.7
        }, 
        "easting": 614228.952, 
        "northing": 140392.55
    }, 
    {
        "dist": 6176.6, 
        "alts": {
            "DTM25": 2214.0
        }, 
        "easting": 614220.952, 
        "northing": 140353.05
    }, 
    {
        "dist": 6217.0, 
        "alts": {
            "DTM25": 2212.7
        }, 
        "easting": 614212.952, 
        "northing": 140313.55
    }, 
    {
        "dist": 6257.3, 
        "alts": {
            "DTM25": 2212.4
        }, 
        "easting": 614204.952, 
        "northing": 140274.05
    }, 
    {
        "dist": 6297.6, 
        "alts": {
            "DTM25": 2213.1
        }, 
        "easting": 614196.952, 
        "northing": 140234.55
    }, 
    {
        "dist": 6337.9, 
        "alts": {
            "DTM25": 2214.9
        }, 
        "easting": 614188.952, 
        "northing": 140195.05
    }, 
    {
        "dist": 6378.2, 
        "alts": {
            "DTM25": 2217.8
        }, 
        "easting": 614180.952, 
        "northing": 140155.55
    }, 
    {
        "dist": 6418.5, 
        "alts": {
            "DTM25": 2221.6
        }, 
        "easting": 614172.952, 
        "northing": 140116.05
    }, 
    {
        "dist": 6458.8, 
        "alts": {
            "DTM25": 2225.8
        }, 
        "easting": 614164.952, 
        "northing": 140076.55
    }, 
    {
        "dist": 6499.1, 
        "alts": {
            "DTM25": 2229.5
        }, 
        "easting": 614156.952, 
        "northing": 140037.05
    }, 
    {
        "dist": 6539.4, 
        "alts": {
            "DTM25": 2232.1
        }, 
        "easting": 614148.952, 
        "northing": 139997.55
    }, 
    {
        "dist": 6579.7, 
        "alts": {
            "DTM25": 2233.4
        }, 
        "easting": 614140.952, 
        "northing": 139958.05
    }, 
    {
        "dist": 6620.0, 
        "alts": {
            "DTM25": 2234.0
        }, 
        "easting": 614132.952, 
        "northing": 139918.55
    }, 
    {
        "dist": 6660.3, 
        "alts": {
            "DTM25": 2233.7
        }, 
        "easting": 614124.952, 
        "northing": 139879.05
    }, 
    {
        "dist": 6700.6, 
        "alts": {
            "DTM25": 2233.8
        }, 
        "easting": 614116.952, 
        "northing": 139839.55
    }, 
    {
        "dist": 6741.4, 
        "alts": {
            "DTM25": 2234.0
        }, 
        "easting": 614103.452, 
        "northing": 139801.05
    }, 
    {
        "dist": 6782.2, 
        "alts": {
            "DTM25": 2234.3
        }, 
        "easting": 614089.952, 
        "northing": 139762.55
    }, 
    {
        "dist": 6823.0, 
        "alts": {
            "DTM25": 2234.9
        }, 
        "easting": 614076.452, 
        "northing": 139724.05
    }, 
    {
        "dist": 6863.8, 
        "alts": {
            "DTM25": 2234.6
        }, 
        "easting": 614062.952, 
        "northing": 139685.55
    }, 
    {
        "dist": 6904.6, 
        "alts": {
            "DTM25": 2235.1
        }, 
        "easting": 614049.452, 
        "northing": 139647.05
    }, 
    {
        "dist": 6945.4, 
        "alts": {
            "DTM25": 2235.2
        }, 
        "easting": 614035.952, 
        "northing": 139608.55
    }, 
    {
        "dist": 6986.2, 
        "alts": {
            "DTM25": 2234.6
        }, 
        "easting": 614022.452, 
        "northing": 139570.05
    }, 
    {
        "dist": 7027.0, 
        "alts": {
            "DTM25": 2234.7
        }, 
        "easting": 614008.952, 
        "northing": 139531.55
    }, 
    {
        "dist": 7067.8, 
        "alts": {
            "DTM25": 2235.9
        }, 
        "easting": 613995.452, 
        "northing": 139493.05
    }, 
    {
        "dist": 7108.6, 
        "alts": {
            "DTM25": 2238.3
        }, 
        "easting": 613981.952, 
        "northing": 139454.55
    }, 
    {
        "dist": 7149.4, 
        "alts": {
            "DTM25": 2242.4
        }, 
        "easting": 613968.452, 
        "northing": 139416.05
    }, 
    {
        "dist": 7190.2, 
        "alts": {
            "DTM25": 2247.2
        }, 
        "easting": 613954.952, 
        "northing": 139377.55
    }, 
    {
        "dist": 7231.0, 
        "alts": {
            "DTM25": 2252.5
        }, 
        "easting": 613941.452, 
        "northing": 139339.05
    }, 
    {
        "dist": 7271.8, 
        "alts": {
            "DTM25": 2258.4
        }, 
        "easting": 613927.952, 
        "northing": 139300.55
    }, 
    {
        "dist": 7312.5, 
        "alts": {
            "DTM25": 2265.8
        }, 
        "easting": 613914.452, 
        "northing": 139262.05
    }, 
    {
        "dist": 7353.3, 
        "alts": {
            "DTM25": 2274.4
        }, 
        "easting": 613900.952, 
        "northing": 139223.55
    }, 
    {
        "dist": 7394.1, 
        "alts": {
            "DTM25": 2281.7
        }, 
        "easting": 613887.452, 
        "northing": 139185.05
    }, 
    {
        "dist": 7434.9, 
        "alts": {
            "DTM25": 2287.7
        }, 
        "easting": 613873.952, 
        "northing": 139146.55
    }, 
    {
        "dist": 7475.7, 
        "alts": {
            "DTM25": 2292.4
        }, 
        "easting": 613860.452, 
        "northing": 139108.05
    }, 
    {
        "dist": 7516.5, 
        "alts": {
            "DTM25": 2295.1
        }, 
        "easting": 613846.952, 
        "northing": 139069.55
    }, 
    {
        "dist": 7556.7, 
        "alts": {
            "DTM25": 2297.6
        }, 
        "easting": 613826.396, 
        "northing": 139035.105
    }, 
    {
        "dist": 7596.8, 
        "alts": {
            "DTM25": 2300.0
        }, 
        "easting": 613805.84, 
        "northing": 139000.661
    }, 
    {
        "dist": 7636.9, 
        "alts": {
            "DTM25": 2302.0
        }, 
        "easting": 613785.285, 
        "northing": 138966.216
    }, 
    {
        "dist": 7677.0, 
        "alts": {
            "DTM25": 2303.3
        }, 
        "easting": 613764.729, 
        "northing": 138931.772
    }, 
    {
        "dist": 7717.1, 
        "alts": {
            "DTM25": 2304.5
        }, 
        "easting": 613744.174, 
        "northing": 138897.327
    }, 
    {
        "dist": 7757.2, 
        "alts": {
            "DTM25": 2304.7
        }, 
        "easting": 613723.618, 
        "northing": 138862.883
    }, 
    {
        "dist": 7797.3, 
        "alts": {
            "DTM25": 2306.6
        }, 
        "easting": 613703.063, 
        "northing": 138828.438
    }, 
    {
        "dist": 7837.4, 
        "alts": {
            "DTM25": 2309.6
        }, 
        "easting": 613682.507, 
        "northing": 138793.994
    }, 
    {
        "dist": 7877.5, 
        "alts": {
            "DTM25": 2312.6
        }, 
        "easting": 613661.952, 
        "northing": 138759.55
    }, 
    {
        "dist": 7917.7, 
        "alts": {
            "DTM25": 2317.6
        }, 
        "easting": 613641.396, 
        "northing": 138725.105
    }, 
    {
        "dist": 7957.8, 
        "alts": {
            "DTM25": 2320.6
        }, 
        "easting": 613620.84, 
        "northing": 138690.661
    }, 
    {
        "dist": 7997.9, 
        "alts": {
            "DTM25": 2322.3
        }, 
        "easting": 613600.285, 
        "northing": 138656.216
    }, 
    {
        "dist": 8038.0, 
        "alts": {
            "DTM25": 2323.5
        }, 
        "easting": 613579.729, 
        "northing": 138621.772
    }, 
    {
        "dist": 8078.1, 
        "alts": {
            "DTM25": 2323.0
        }, 
        "easting": 613559.174, 
        "northing": 138587.327
    }, 
    {
        "dist": 8118.2, 
        "alts": {
            "DTM25": 2321.0
        }, 
        "easting": 613538.618, 
        "northing": 138552.883
    }, 
    {
        "dist": 8158.3, 
        "alts": {
            "DTM25": 2319.3
        }, 
        "easting": 613518.063, 
        "northing": 138518.438
    }, 
    {
        "dist": 8198.4, 
        "alts": {
            "DTM25": 2316.3
        }, 
        "easting": 613497.507, 
        "northing": 138483.994
    }, 
    {
        "dist": 8238.6, 
        "alts": {
            "DTM25": 2314.1
        }, 
        "easting": 613476.952, 
        "northing": 138449.55
    }
]
